{
  "project_info": {
    "project_number": "954613880103",
    "firebase_url": "https://sebastian-denis-app.firebaseio.com",
    "project_id": "sebastian-denis-app",
    "storage_bucket": "sebastian-denis-app.appspot.com"
  },
  "client": [
    {
      "client_info": {
        "mobilesdk_app_id": "1:954613880103:android:5fe3c2df2ad46ced",
        "android_client_info": {
          "package_name": "com.sebastiandenis.sebastiandenisapp"
        }
      },
      "oauth_client": [
        {
          "client_id": "954613880103-39tukba3lfann9fr7t4rn480iboko4pd.apps.googleusercontent.com",
          "client_type": 3
        }
      ],
      "api_key": [
        {
          "current_key": "AIzaSyDQym4ag2k7Hw8rKdlW7tmR_VnMO0mCVVs"
        }
      ],
      "services": {
        "analytics_service": {
          "status": 1
        },
        "appinvite_service": {
          "status": 1,
          "other_platform_oauth_client": []
        },
        "ads_service": {
          "status": 2
        }
      }
    }
  ],
  "configuration_version": "1"
}